openbb_econometrics/__init__.py
openbb_econometrics/econometrics_router.py
openbb_econometrics/econometrics_views.py
openbb_econometrics/py.typed
openbb_econometrics/utils.py
openbb_econometrics-1.6.1.dist-info/METADATA
openbb_econometrics-1.6.1.dist-info/WHEEL
openbb_econometrics-1.6.1.dist-info/entry_points.txt
openbb_econometrics-1.6.1.dist-info/RECORD
