Metadata-Version: 2.4
Name: openbb-econometrics
Version: 1.6.1
Summary: Econometrics Toolkit for OpenBB
License: AGPL-3.0-only
Author: OpenBB Team
Author-email: hello@openbb.co
Requires-Python: >=3.10,<3.14
Classifier: License :: OSI Approved :: GNU Affero General Public License v3
Classifier: Programming Language :: Python :: 3
Classifier: Programming Language :: Python :: 3.10
Classifier: Programming Language :: Python :: 3.11
Classifier: Programming Language :: Python :: 3.12
Classifier: Programming Language :: Python :: 3.13
Requires-Dist: arch (>=7.2,<8.0)
Requires-Dist: linearmodels (>=6,<7)
Requires-Dist: openbb-core (>=1.5.7,<2.0.0)
Requires-Dist: pandas-ta-openbb (>=0.4.20,<0.5.0)
